paeio/__init__.py
paeio/io.py
paeio/parallelism.py
paeio/path.py
paeio/versioned.py
paeio-0.1.dist-info/LICENSE
paeio-0.1.dist-info/METADATA
paeio-0.1.dist-info/WHEEL
paeio-0.1.dist-info/top_level.txt
paeio-0.1.dist-info/RECORD
