Metadata-Version: 2.1
Name: paeio
Version: 0.1
Summary: Utilities library for read/write operations and general data cleaning routines
Author-email: João Pedro Alves <jotapedro1997@gmail.com>
Project-URL: Homepage, https://github.com/jotap123/paeio/tree/develop
Project-URL: Issues, https://github.com/jotap123/paeio/issues
Project-URL: Linkedin_JP, https://www.linkedin.com/in/jp111/
Classifier: Programming Language :: Python :: 3
Classifier: License :: OSI Approved :: MIT License
Classifier: Operating System :: OS Independent
Classifier: Development Status :: 5 - Production/Stable
Requires-Python: >=3.7.1
License-File: LICENSE
Requires-Dist: azure-identity
Requires-Dist: azure-storage-file-datalake
Requires-Dist: joblib
Requires-Dist: numpy
Requires-Dist: pandas
Requires-Dist: pyarrow
Requires-Dist: openpyxl
Requires-Dist: python-dotenv
